torchopenl3/__init__.py
torchopenl3/__main__.py
torchopenl3/cli.py
torchopenl3/core.py
torchopenl3/models.py
torchopenl3/torchopenl3_exceptions.py
torchopenl3/utils.py
torchopenl3/version.py
torchopenl3-1.0.1.dist-info/LICENSE
torchopenl3-1.0.1.dist-info/METADATA
torchopenl3-1.0.1.dist-info/WHEEL
torchopenl3-1.0.1.dist-info/entry_points.txt
torchopenl3-1.0.1.dist-info/top_level.txt
torchopenl3-1.0.1.dist-info/RECORD
