Metadata-Version: 2.1
Name: torchopenl3
Version: 1.0.1
Summary: Deep audio and image embeddings, based on Look, Listen, and Learn approach Pytorch
Home-page: https://github.com/torchopenl3/torchopenl3/
Author: Humair Raj Khan and Gyanendra Das
Author-email: gyanendralucky9337@gmail.com
License: MIT
Classifier: Development Status :: 3 - Alpha
Classifier: License :: OSI Approved :: Apache Software License
Classifier: Intended Audience :: Developers
Classifier: Intended Audience :: Science/Research
Classifier: Topic :: Multimedia :: Sound/Audio :: Analysis
Classifier: Programming Language :: Python :: 3.6
License-File: LICENSE
Requires-Dist: numpy (>=1.13.0)
Requires-Dist: scipy (>=0.19.1)
Requires-Dist: soundfile
Requires-Dist: resampy (<0.3.0,>=0.2.1)
Requires-Dist: torch (>=1.4.0)
Requires-Dist: nnAudio (>=0.2.4)
Requires-Dist: julius (>=0.2.5)
Requires-Dist: librosa
Provides-Extra: dev
Requires-Dist: pytest ; extra == 'dev'
Requires-Dist: pytest-cov ; extra == 'dev'
Requires-Dist: Cython (>=0.23.4) ; extra == 'dev'
Requires-Dist: openl3 (==0.3.1) ; extra == 'dev'
Requires-Dist: kapre (==0.1.4) ; extra == 'dev'
Requires-Dist: h5py (==2.10.0) ; extra == 'dev'
Requires-Dist: tensorflow (<1.14) ; extra == 'dev'
Requires-Dist: requests ; extra == 'dev'
Requires-Dist: tqdm ; extra == 'dev'
Requires-Dist: pre-commit ; extra == 'dev'
Requires-Dist: nbstripout (==0.3.9) ; extra == 'dev'
Requires-Dist: black (==20.8b1) ; extra == 'dev'
Requires-Dist: jupytext (==v1.10.3) ; extra == 'dev'
Requires-Dist: protobuf (<=3.20.1) ; extra == 'dev'
Provides-Extra: test
Requires-Dist: pytest ; extra == 'test'
Requires-Dist: pytest-cov ; extra == 'test'
Requires-Dist: Cython (>=0.23.4) ; extra == 'test'
Requires-Dist: openl3 (==0.3.1) ; extra == 'test'
Requires-Dist: kapre (==0.1.4) ; extra == 'test'
Requires-Dist: h5py (==2.10.0) ; extra == 'test'
Requires-Dist: tensorflow (<1.14) ; extra == 'test'
Requires-Dist: requests ; extra == 'test'
Requires-Dist: tqdm ; extra == 'test'
Requires-Dist: protobuf (<=3.20.1) ; extra == 'test'
